mongo_queue/__init__.py
mongo_queue/job.py
mongo_queue/lock.py
mongo_queue/queue.py
mongo_queue/test-parallel.py
mongo_queue/test.py
mongo_queue_service-0.2.1.dist-info/LICENSE
mongo_queue_service-0.2.1.dist-info/METADATA
mongo_queue_service-0.2.1.dist-info/WHEEL
mongo_queue_service-0.2.1.dist-info/top_level.txt
mongo_queue_service-0.2.1.dist-info/RECORD
