Metadata-Version: 2.1
Name: mongo_queue_service
Version: 0.2.1
Summary: Queue service built on top of mongo.
Home-page: https://github.com/shunyeka/mongo_queue/
Download-URL: https://github.com/shunyeka/mongo_queue/archive/v0.1.8.tar.gz
Author: Amit Chotaliya
Author-email: amit@shunyeka.com
Keywords: mongo,queue,priority queue,task queue
Classifier: Programming Language :: Python :: 3
Classifier: License :: OSI Approved :: MIT License
Classifier: Operating System :: OS Independent
Requires-Python: >=3.6
License-File: LICENSE
Requires-Dist: pymongo
